karabo_aravis_cameras/aravisCameras/libaravisCameras.so
karabo_aravis_cameras/bin/karabo-aravis-cameras-server
karabo_aravis_cameras/shims/entrypoints.py
karabo_aravis_cameras.libs/libamqpcpp-38f6058d.so.4.3
karabo_aravis_cameras.libs/libaravis-0-d261e044.8.so.0.8.31
karabo_aravis_cameras.libs/libaravisCameras-72af6e04.so
karabo_aravis_cameras.libs/libblkid-a9167753.so.1.1.0
karabo_aravis_cameras.libs/libboost_atomic-306ed786.so.1.88.0
karabo_aravis_cameras.libs/libboost_chrono-bdd922c8.so.1.88.0
karabo_aravis_cameras.libs/libboost_container-ada431f4.so.1.88.0
karabo_aravis_cameras.libs/libboost_date_time-5de398e8.so.1.88.0
karabo_aravis_cameras.libs/libboost_regex-0485f5e1.so.1.88.0
karabo_aravis_cameras.libs/libboost_system-51075d83.so.1.88.0
karabo_aravis_cameras.libs/libboost_thread-38335b7b.so.1.88.0
karabo_aravis_cameras.libs/libcrypto-319949f2.so.1.1
karabo_aravis_cameras.libs/libcurl-80a04cbc.so.4
karabo_aravis_cameras.libs/libdate-tz-d3340c59.so.3
karabo_aravis_cameras.libs/libffi-3a37023a.so.6.0.2
karabo_aravis_cameras.libs/libfmt-c961d355.so.10
karabo_aravis_cameras.libs/libgfortran-8f1e9814.so.5.0.0
karabo_aravis_cameras.libs/libgio-2-10fed6c5.0.so.0.5600.4
karabo_aravis_cameras.libs/libgmodule-2-6c5d2a3f.0.so.0.5600.4
karabo_aravis_cameras.libs/libgmp-d944b113.so.10.3.2
karabo_aravis_cameras.libs/libgnutls-5ac79744.so.30.28.2
karabo_aravis_cameras.libs/libhogweed-cd4c53be.so.4.5
karabo_aravis_cameras.libs/libidn2-2f4a5893.so.0.3.6
karabo_aravis_cameras.libs/libimageSource-9065e3ed.so
karabo_aravis_cameras.libs/libjpeg-e87d2658.so.62.2.0
karabo_aravis_cameras.libs/libkarabo-5e87e71d.so.3
karabo_aravis_cameras.libs/liblzma-51a76f52.so.5.2.4
karabo_aravis_cameras.libs/libmount-ec61bd71.so.1.1.0
karabo_aravis_cameras.libs/libnettle-37944285.so.6.5
karabo_aravis_cameras.libs/libopenblas-r0-11edc3fa.3.15.so
karabo_aravis_cameras.libs/libopencv_core-e07fff4f.so.3.4.6
karabo_aravis_cameras-3.1.0.dist-info/METADATA
karabo_aravis_cameras-3.1.0.dist-info/WHEEL
karabo_aravis_cameras-3.1.0.dist-info/entry_points.txt
karabo_aravis_cameras-3.1.0.dist-info/RECORD
karabo_aravis_cameras-3.1.0.dist-info/licenses/LICENSE.md
