Metadata-Version: 2.4
Name: karabo-aravis-cameras
Version: 3.1.0
Summary: A Karabo device to control and acquire data from Aravis compatible cameras.
Keywords: Karabo,SCADA,camera,control system,aravis
Author-Email: European XFEL GmbH <opensource@xfel.eu>
Maintainer-Email: "A. Parenti" <andrea.parenti@xfel.eu>
License-Expression: GPL-3.0
Classifier: Development Status :: 5 - Production/Stable
Classifier: Intended Audience :: Developers
Classifier: Intended Audience :: Science/Research
Project-URL: Homepage, https://github.com/European-XFEL/Karabo-aravisCameras
Project-URL: Bug Reports, https://github.com/European-XFEL/Karabo-aravisCameras/issues
Project-URL: Source, https://github.com/European-XFEL/Karabo-aravisCameras
Requires-Python: ==3.12.*
Requires-Dist: karabo[cpp]
